cantaloupe/__init__.py
cantaloupe/__main__.py
cantaloupe/enums.py
cantaloupe/errors.py
cantaloupe/hookspecs.py
cantaloupe/host.py
cantaloupe/loaders.py
cantaloupe/logger.py
cantaloupe/models.py
cantaloupe/plugins/__init__.py
cantaloupe/plugins/core_cli.py
cantaloupe/plugins/core_error_handling.py
cantaloupe/plugins/core_framework.py
cantaloupe-0.1.4.dist-info/METADATA
cantaloupe-0.1.4.dist-info/WHEEL
cantaloupe-0.1.4.dist-info/entry_points.txt
cantaloupe-0.1.4.dist-info/RECORD
