Metadata-Version: 2.1
Name: cantaloupe
Version: 0.1.4
Summary: An extensible framework for building browser automations.
Author: Lemuel Boyce
Author-email: lemuelboyce@gmail.com
Requires-Python: >=3.10,<4.0
Classifier: Programming Language :: Python :: 3
Classifier: Programming Language :: Python :: 3.10
Classifier: Programming Language :: Python :: 3.11
Requires-Dist: pluggy (>=1.2.0,<2.0.0)
Requires-Dist: pydantic (>=2.0.3,<3.0.0)
